{
  "updatedAt": "2026-04-13",
  "sources": [
    "ORCID",
    "NIST"
  ],
  "publications": [
    {
      "title": "Multiverse: A Simulator for Evaluating Entanglement Routing in Quantum Networks",
      "published": "2026-01-01",
      "venue": "IEEE Internet Computing",
      "authors": "",
      "links": [
        {
          "label": "DOI",
          "href": "https://doi.org/10.1109/MIC.2026.3651126"
        }
      ],
      "source": "ORCID"
    },
    {
      "title": "Scalable Time-Tagged Data Acquisition for Entanglement Distribution in Quantum Networks",
      "published": "2025-08-30",
      "venue": "2025 IEEE International Conference on Quantum Computing and Engineering (QCE)",
      "authors": "",
      "links": [
        {
          "label": "DOI",
          "href": "https://doi.org/10.1109/qce65121.2025.00127"
        }
      ],
      "source": "ORCID"
    },
    {
      "title": "Towards Optimal Orders for Entanglement Swapping in Path Graphs: A Greedy Approach",
      "published": "2025-08-30",
      "venue": "2025 IEEE International Conference on Quantum Computing and Engineering (QCE)",
      "authors": "",
      "links": [
        {
          "label": "DOI",
          "href": "https://doi.org/10.1109/qce65121.2025.00138"
        }
      ],
      "source": "ORCID"
    },
    {
      "title": "A Data Collection Platform for Network Management",
      "published": "2024-04-02",
      "venue": "2023 20th ACS/IEEE International Conference on Computer Systems and Applications (AICCSA)",
      "authors": "Amar Abane, Abdella Battou, Abderrahim Amlou, Tao Zhang",
      "links": [
        {
          "label": "DOI",
          "href": "https://doi.org/10.1109/aiccsa59173.2023.10479236"
        },
        {
          "label": "NIST",
          "href": "https://www.nist.gov/publications/data-collection-platform-network-management"
        }
      ],
      "source": "ORCID",
      "citationCount": 0
    },
    {
      "title": "Automated Network Programmability Using OpenConfig YANG Models and NETCONF Protocol",
      "published": "2024-04-02",
      "venue": "2023 20th ACS/IEEE International Conference on Computer Systems and Applications (AICCSA)",
      "authors": "Abderrahim Amlou, Amar Abane, Mheni Merzouki, Lydia Ait Oucheggou, Zineb Maasaoui, Abdella Battou",
      "links": [
        {
          "label": "DOI",
          "href": "https://doi.org/10.1109/aiccsa59173.2023.10479244"
        },
        {
          "label": "NIST",
          "href": "https://www.nist.gov/publications/automated-network-programmability-using-openconfig-yang-models-and-netconf-protocol"
        }
      ],
      "source": "ORCID",
      "citationCount": 0
    }
  ]
}